pydantic_walk_core_schema/__init__.py
pydantic_walk_core_schema/py.typed
pydantic_walk_core_schema/walk_core_schema.py
pydantic_walk_core_schema-1.0.0.dist-info/METADATA
pydantic_walk_core_schema-1.0.0.dist-info/WHEEL
pydantic_walk_core_schema-1.0.0.dist-info/licenses/LICENSE.txt
pydantic_walk_core_schema-1.0.0.dist-info/RECORD
