Metadata-Version: 2.4
Name: pydantic_walk_core_schema
Version: 1.0.0
Summary: Dependency injection without the boilerplate.
Project-URL: Source, https://github.com/rmorshea/pydantic-walk-core-schema
Author-email: Ryan Morshead <ryan.morshead@gmail.com>
License: MIT License
License-File: LICENSE.txt
Classifier: Development Status :: 4 - Beta
Classifier: Programming Language :: Python
Requires-Python: <4,>=3.11
Requires-Dist: pydantic-core>=2.27.2
